LICENSE
MANIFEST.in
README.md
setup.py
tests/__init__.py
tests/http_response_catcher.py
tests/test_helper.py
tests/controllers/__init__.py
tests/controllers/controller_test_base.py
tests/controllers/test_api_controller.py
ubindrzvyo/__init__.py
ubindrzvyo/api_helper.py
ubindrzvyo/configuration.py
ubindrzvyo/decorators.py
ubindrzvyo/ubindrzvyo_client.py
ubindrzvyo.egg-info/PKG-INFO
ubindrzvyo.egg-info/SOURCES.txt
ubindrzvyo.egg-info/dependency_links.txt
ubindrzvyo.egg-info/requires.txt
ubindrzvyo.egg-info/top_level.txt
ubindrzvyo/controllers/__init__.py
ubindrzvyo/controllers/api_controller.py
ubindrzvyo/controllers/base_controller.py
ubindrzvyo/exceptions/__init__.py
ubindrzvyo/exceptions/api_exception.py
ubindrzvyo/http/__init__.py
ubindrzvyo/http/http_call_back.py
ubindrzvyo/http/http_client.py
ubindrzvyo/http/http_context.py
ubindrzvyo/http/http_method_enum.py
ubindrzvyo/http/http_request.py
ubindrzvyo/http/http_response.py
ubindrzvyo/http/requests_client.py
ubindrzvyo/http/auth/__init__.py
ubindrzvyo/http/auth/basic_auth.py
ubindrzvyo/models/__init__.py
ubindrzvyo/models/suite_code_enum.py